edxml_schema/__init__.py
edxml_schema/schema/edxml-schema-3.0.0.rng
edxml_schema-3.0.0.dist-info/METADATA
edxml_schema-3.0.0.dist-info/WHEEL
edxml_schema-3.0.0.dist-info/top_level.txt
edxml_schema-3.0.0.dist-info/RECORD
