Metadata-Version: 2.1
Name: edxml-schema
Version: 3.0.0
Summary: The RelaxNG schema that is part of the EDXML specification
Home-page: https://github.com/edxml/schema
Author: Dik Takken
Author-email: dik.takken@edxml.org
Classifier: Programming Language :: Python
Classifier: License :: OSI Approved :: MIT License
Classifier: Operating System :: OS Independent
Classifier: Development Status :: 5 - Production/Stable
Classifier: Topic :: Scientific/Engineering :: Artificial Intelligence
